claude_trace_viewer-0.2.1.dist-info/licenses/LICENSE
trace_viewer/__init__.py
trace_viewer/__main__.py
trace_viewer/parser.py
trace_viewer/server.py
trace_viewer/subagent_detector.py
trace_viewer/static/app.js
trace_viewer/static/style.css
trace_viewer/static/syntax-highlight.css
trace_viewer/static/js/json-viewer/json-viewer.css
trace_viewer/static/js/json-viewer/json-viewer.js
trace_viewer/templates/index.html
claude_trace_viewer-0.2.1.dist-info/METADATA
claude_trace_viewer-0.2.1.dist-info/WHEEL
claude_trace_viewer-0.2.1.dist-info/entry_points.txt
claude_trace_viewer-0.2.1.dist-info/top_level.txt
claude_trace_viewer-0.2.1.dist-info/RECORD
