Metadata-Version: 2.4
Name: claude-trace-viewer
Version: 0.2.1
Summary: An alternate web-based viewer for logs generated by @mariozechner/claude-trace
Author: Brian Krabach
License: MIT
Project-URL: Homepage, https://github.com/bkrabach/claude-trace-viewer
Project-URL: Repository, https://github.com/bkrabach/claude-trace-viewer
Keywords: claude,trace,viewer,debugging,visualization,claude-ai,anthropic,claude-trace,log-viewer
Classifier: Development Status :: 3 - Alpha
Classifier: Intended Audience :: Developers
Classifier: License :: OSI Approved :: MIT License
Classifier: Programming Language :: Python :: 3
Classifier: Programming Language :: Python :: 3.11
Classifier: Programming Language :: Python :: 3.12
Classifier: Topic :: Software Development :: Debuggers
Classifier: Topic :: Software Development :: Libraries :: Python Modules
Classifier: Environment :: Web Environment
Classifier: Framework :: Flask
Requires-Python: >=3.11
License-File: LICENSE
Requires-Dist: flask>=3.0.0
Provides-Extra: dev
Requires-Dist: pytest>=8.4.2; extra == "dev"
Requires-Dist: ruff>=0.8.0; extra == "dev"
Requires-Dist: build>=1.2.2; extra == "dev"
Dynamic: license-file
